{
    "id":  "bulletin06-dossinterview-532533",
    "legacy_path":  "bulletin06-dossinterview-532533.html",
    "legacy_name":  "bulletin06-dossinterview-532533",
    "canonical_path":  "/bulletin/interviews/bulletin06-dossinterview-532533/",
    "title":  "Doss - Alius",
    "description":  "Cinco Sins of Psychedelic Research",
    "section":  "bulletin",
    "subcategory":  "interviews",
    "layout":  "article",
    "nav_group":  "bulletin",
    "order":  0,
    "body_fragment":  "content/bulletin/interviews/bulletin06-dossinterview-532533/body.html",
    "head_fragment":  "content/bulletin/interviews/bulletin06-dossinterview-532533/head.raw.html",
    "source_html":  "content/bulletin/interviews/bulletin06-dossinterview-532533/original.html",
    "page_css":  "",
    "page_js":  "",
    "html_tag_attributes":  "lang=\"en\"",
    "body_tag_attributes":  "class=\"no-header  wsite-page-bulletin06-dossinterview-532533  full-width-on  wsite-theme-light\"",
    "status":  "published",
    "redirect_legacy":  true
}
